android_device_manager/__init__.py
android_device_manager/adb/__init__.py
android_device_manager/adb/client.py
android_device_manager/adb/exceptions.py
android_device_manager/android_device.py
android_device_manager/avd/__init__.py
android_device_manager/avd/config.py
android_device_manager/avd/exceptions.py
android_device_manager/avd/manager.py
android_device_manager/constants.py
android_device_manager/emulator/__init__.py
android_device_manager/emulator/config.py
android_device_manager/emulator/exceptions.py
android_device_manager/emulator/manager.py
android_device_manager/exceptions.py
android_device_manager/py.typed
android_device_manager/utils/__init__.py
android_device_manager/utils/android_sdk.py
android_device_manager/utils/sdk_manager.py
android_device_manager/utils/validation.py
android_device_manager-1.0.2.dist-info/WHEEL
android_device_manager-1.0.2.dist-info/METADATA
android_device_manager-1.0.2.dist-info/RECORD
