Metadata-Version: 2.3
Name: android-device-manager
Version: 1.0.2
Summary: Android Device Manager is a Python library for creating, launching, and managing Android device programmatically. 
Author: Jérémy Woirhaye
Author-email: Jérémy Woirhaye <jerem.woirhaye@gmail.com>
Maintainer: Jérémy Woirhaye
Maintainer-email: Jérémy Woirhaye <jerem.woirhaye@gmail.com>
Requires-Python: >=3.10
Project-URL: Documentation, https://jwoirhaye.com/android-device-manager-python/
Project-URL: Homepage, https://github.com/jwoirhaye/android-device-manager-python
Project-URL: Issues, https://github.com/jwoirhaye/android-device-manager-python/issues
Project-URL: Source, https://github.com/jwoirhaye/android-device-manager-python
